bpdp_cli/__init__.py
bpdp_cli/__main__.py
bpdp_cli-0.1.0.dist-info/METADATA
bpdp_cli-0.1.0.dist-info/WHEEL
bpdp_cli-0.1.0.dist-info/entry_points.txt
bpdp_cli-0.1.0.dist-info/licenses/LICENSE.txt
bpdp_cli-0.1.0.dist-info/RECORD
