Metadata-Version: 2.4
Name: bpdp_cli
Version: 0.1.0
Summary: CLI of BPDP
Author-email: "林彥廷(Yen-Ting, Lin)" <d26923050@gmail.com>
License-Expression: BSD-3-Clause
License-File: LICENSE.txt
Classifier: Programming Language :: Python :: 3
Classifier: Topic :: Multimedia :: Sound/Audio :: Analysis
Classifier: Topic :: Multimedia :: Sound/Audio :: Speech
Requires-Python: >=3.10
Requires-Dist: bpdp>=0.1.0
Requires-Dist: torchaudio>=2.0.0
